[{"id":"1","url":"http:\/\/glsmscit.org\/cybershadez\/images\/portfolio\/2018\/1.jpg"},{"id":"2","url":"http:\/\/glsmscit.org\/cybershadez\/images\/portfolio\/2018\/2.jpg"},{"id":"3","url":"http:\/\/glsmscit.org\/cybershadez\/images\/portfolio\/2018\/3.jpg"},{"id":"4","url":"http:\/\/glsmscit.org\/cybershadez\/images\/portfolio\/2017\/1.jpg"},{"id":"5","url":"http:\/\/glsmscit.org\/cybershadez\/images\/portfolio\/2017\/2.jpg"},{"id":"6","url":"http:\/\/glsmscit.org\/cybershadez\/images\/portfolio\/2017\/3.jpg"},{"id":"7","url":"http:\/\/glsmscit.org\/cybershadez\/images\/portfolio\/2016\/1.jpg"},{"id":"8","url":"http:\/\/glsmscit.org\/cybershadez\/images\/portfolio\/2016\/2.jpg"},{"id":"9","url":"http:\/\/glsmscit.org\/cybershadez\/images\/portfolio\/2016\/3.jpg"},{"id":"10","url":"http:\/\/glsmscit.org\/cybershadez\/images\/portfolio\/2015\/1.jpg"},{"id":"11","url":"http:\/\/glsmscit.org\/cybershadez\/images\/portfolio\/2015\/2.jpg"},{"id":"12","url":"http:\/\/glsmscit.org\/cybershadez\/images\/portfolio\/2015\/1.jpg"}]
